power01_mul/__init__.py
power01_mul/mul.py
power01_mul-0.1.1.dist-info/METADATA
power01_mul-0.1.1.dist-info/WHEEL
power01_mul-0.1.1.dist-info/entry_points.txt
power01_mul-0.1.1.dist-info/top_level.txt
power01_mul-0.1.1.dist-info/RECORD
