Metadata-Version: 2.1
Name: power01_mul
Version: 0.1.1
Summary: Default template for PDM package
Author-email: sooj1n <sujin19371@gmail.com>
License: MIT
Requires-Python: >=3.9
